nonebot_plugin_logpile/__init__.py
nonebot_plugin_logpile/config.py
nonebot_plugin_logpile-0.2.1.dist-info/WHEEL
nonebot_plugin_logpile-0.2.1.dist-info/METADATA
nonebot_plugin_logpile-0.2.1.dist-info/licenses/LICENSE
nonebot_plugin_logpile-0.2.1.dist-info/RECORD
