Metadata-Version: 2.1
Name: nonebot-plugin-logpile
Version: 0.2.1
Summary: NoneBot2 local log files
License: MIT
Author-email: Akirami <Akiramiaya@outlook.com>
Requires-Python: >=3.8
Requires-Dist: nonebot2>=2.0.0rc4
Project-URL: Homepage, https://github.com/A-kirami/nonebot-plugin-logpile
Project-URL: Repository, https://github.com/A-kirami/nonebot-plugin-logpile
